qsosed/__init__.py
qsosed/constants.py
qsosed/plotting.py
qsosed/sed.py
qsosed/xspec_routines.py
qsosed-0.0.1.dev60.dist-info/AUTHORS
qsosed-0.0.1.dev60.dist-info/LICENSE
qsosed-0.0.1.dev60.dist-info/METADATA
qsosed-0.0.1.dev60.dist-info/WHEEL
qsosed-0.0.1.dev60.dist-info/pbr.json
qsosed-0.0.1.dev60.dist-info/top_level.txt
qsosed-0.0.1.dev60.dist-info/RECORD
