Metadata-Version: 2.1
Name: qsosed
Version: 0.0.1.dev60
Summary: A physical model for SED of QSO.
Home-page: https://github.com/arnauqb/qwind
Author: Arnau Quera-Bofarull
Author-email: arnau.quera-bofarull@durham.ac.uk
License: GPL
Platform: UNKNOWN
Requires-Python: >=3.6
Requires-Dist: astropy (>=3.2.1)
Requires-Dist: numpy (>=1.16.4)
Requires-Dist: scipy (>=1.3.0)
